wsgissi.py
wsgissi_skot-0.8.dist-info/DESCRIPTION.rst
wsgissi_skot-0.8.dist-info/METADATA
wsgissi_skot-0.8.dist-info/RECORD
wsgissi_skot-0.8.dist-info/WHEEL
wsgissi_skot-0.8.dist-info/metadata.json
wsgissi_skot-0.8.dist-info/top_level.txt
